odoo/addons/ddmrp_exclude_moves_adu_calc/README.rst
odoo/addons/ddmrp_exclude_moves_adu_calc/__init__.py
odoo/addons/ddmrp_exclude_moves_adu_calc/__manifest__.py
odoo/addons/ddmrp_exclude_moves_adu_calc/i18n/ddmrp_exclude_moves_adu_calc.pot
odoo/addons/ddmrp_exclude_moves_adu_calc/i18n/es.po
odoo/addons/ddmrp_exclude_moves_adu_calc/i18n/fr.po
odoo/addons/ddmrp_exclude_moves_adu_calc/i18n/it.po
odoo/addons/ddmrp_exclude_moves_adu_calc/i18n/pt_BR.po
odoo/addons/ddmrp_exclude_moves_adu_calc/models/__init__.py
odoo/addons/ddmrp_exclude_moves_adu_calc/models/stock_buffer.py
odoo/addons/ddmrp_exclude_moves_adu_calc/models/stock_location.py
odoo/addons/ddmrp_exclude_moves_adu_calc/models/stock_move.py
odoo/addons/ddmrp_exclude_moves_adu_calc/readme/CONTRIBUTORS.md
odoo/addons/ddmrp_exclude_moves_adu_calc/readme/CREDITS.md
odoo/addons/ddmrp_exclude_moves_adu_calc/readme/DESCRIPTION.md
odoo/addons/ddmrp_exclude_moves_adu_calc/readme/HISTORY.md
odoo/addons/ddmrp_exclude_moves_adu_calc/readme/USAGE.md
odoo/addons/ddmrp_exclude_moves_adu_calc/static/description/icon.png
odoo/addons/ddmrp_exclude_moves_adu_calc/static/description/index.html
odoo/addons/ddmrp_exclude_moves_adu_calc/tests/__init__.py
odoo/addons/ddmrp_exclude_moves_adu_calc/tests/test_ddmrp.py
odoo/addons/ddmrp_exclude_moves_adu_calc/views/stock_location_view.xml
odoo/addons/ddmrp_exclude_moves_adu_calc/views/stock_move_view.xml
odoo_addon_ddmrp_exclude_moves_adu_calc-18.0.1.1.1.dist-info/METADATA
odoo_addon_ddmrp_exclude_moves_adu_calc-18.0.1.1.1.dist-info/WHEEL
odoo_addon_ddmrp_exclude_moves_adu_calc-18.0.1.1.1.dist-info/top_level.txt
odoo_addon_ddmrp_exclude_moves_adu_calc-18.0.1.1.1.dist-info/RECORD
